<?xml version="1.0" encoding="UTF-8"?>
<!DOCTYPE mapper PUBLIC "-//mybatis.org//DTD Mapper 3.0//EN" "http://mybatis.org/dtd/mybatis-3-mapper.dtd">
<mapper namespace="com.lnsoft.module.qx.qxzhyj.mapper.BgwAppQxQxzhyjMapper">
  <resultMap id="BaseResultMap" type="com.lnsoft.module.qx.qxzhyj.pojo.BgwAppQxQxzhyj">
    <!--
      WARNING - @mbggenerated
      This element is automatically generated by MyBatis Generator, do not modify.
      This element was generated on Fri Nov 16 16:29:01 CST 2018.
    -->
    <result column="YJXH" jdbcType="DECIMAL" property="yjxh" />
    <result column="AREANAME" jdbcType="VARCHAR" property="areaname" />
    <result column="SIGNALNAME" jdbcType="VARCHAR" property="signalname" />
    <result column="YJTITLE" jdbcType="VARCHAR" property="yjtitle" />
    <result column="YJCONTENT" jdbcType="VARCHAR" property="yjcontent" />
    <result column="ISSUEDATE" jdbcType="TIMESTAMP" property="issuedate" />
    <result column="FREETIME" jdbcType="TIMESTAMP" property="freetime" />
    <result column="STA_NAME" jdbcType="VARCHAR" property="staName" />
    <result column="CODE" jdbcType="VARCHAR" property="code" />
    <result column="CODES" jdbcType="VARCHAR" property="codes" />
    <result column="SIGNALTYPE" jdbcType="VARCHAR" property="signaltype" />
    <result column="AREA" jdbcType="VARCHAR" property="area" />
  </resultMap>
  <sql id="Example_Where_Clause">
    <!--
      WARNING - @mbggenerated
      This element is automatically generated by MyBatis Generator, do not modify.
      This element was generated on Fri Nov 16 16:29:01 CST 2018.
    -->
    <where>
      <foreach collection="oredCriteria" item="criteria" separator="or">
        <if test="criteria.valid">
          <trim prefix="(" prefixOverrides="and" suffix=")">
            <foreach collection="criteria.criteria" item="criterion">
              <choose>
                <when test="criterion.noValue">
                  and ${criterion.condition}
                </when>
                <when test="criterion.singleValue">
                  and ${criterion.condition} #{criterion.value}
                </when>
                <when test="criterion.betweenValue">
                  and ${criterion.condition} #{criterion.value} and #{criterion.secondValue}
                </when>
                <when test="criterion.listValue">
                  and ${criterion.condition}
                  <foreach close=")" collection="criterion.value" item="listItem" open="(" separator=",">
                    #{listItem}
                  </foreach>
                </when>
              </choose>
            </foreach>
          </trim>
        </if>
      </foreach>
    </where>
  </sql>
  <sql id="Update_By_Example_Where_Clause">
    <!--
      WARNING - @mbggenerated
      This element is automatically generated by MyBatis Generator, do not modify.
      This element was generated on Fri Nov 16 16:29:01 CST 2018.
    -->
    <where>
      <foreach collection="example.oredCriteria" item="criteria" separator="or">
        <if test="criteria.valid">
          <trim prefix="(" prefixOverrides="and" suffix=")">
            <foreach collection="criteria.criteria" item="criterion">
              <choose>
                <when test="criterion.noValue">
                  and ${criterion.condition}
                </when>
                <when test="criterion.singleValue">
                  and ${criterion.condition} #{criterion.value}
                </when>
                <when test="criterion.betweenValue">
                  and ${criterion.condition} #{criterion.value} and #{criterion.secondValue}
                </when>
                <when test="criterion.listValue">
                  and ${criterion.condition}
                  <foreach close=")" collection="criterion.value" item="listItem" open="(" separator=",">
                    #{listItem}
                  </foreach>
                </when>
              </choose>
            </foreach>
          </trim>
        </if>
      </foreach>
    </where>
  </sql>
  <sql id="Base_Column_List">
    <!--
      WARNING - @mbggenerated
      This element is automatically generated by MyBatis Generator, do not modify.
      This element was generated on Fri Nov 16 16:29:01 CST 2018.
    -->
    YJXH, AREANAME, SIGNALNAME, YJTITLE, YJCONTENT, ISSUEDATE, FREETIME, STA_NAME, CODE, 
    CODES, SIGNALTYPE, AREA
  </sql>
  <select id="selectByExample" parameterType="com.lnsoft.module.qx.qxzhyj.pojo.BgwAppQxQxzhyjExample" resultMap="BaseResultMap">
    <!--
      WARNING - @mbggenerated
      This element is automatically generated by MyBatis Generator, do not modify.
      This element was generated on Fri Nov 16 16:29:01 CST 2018.
    -->
    select
    <if test="distinct">
      distinct
    </if>
    <include refid="Base_Column_List" />
    from BGW_APP_QX_QXZHYJ
    <if test="_parameter != null">
      <include refid="Example_Where_Clause" />
    </if>
    <if test="orderByClause != null">
      order by ${orderByClause}
    </if>
  </select>
  <delete id="deleteByExample" parameterType="com.lnsoft.module.qx.qxzhyj.pojo.BgwAppQxQxzhyjExample">
    <!--
      WARNING - @mbggenerated
      This element is automatically generated by MyBatis Generator, do not modify.
      This element was generated on Fri Nov 16 16:29:01 CST 2018.
    -->
    delete from BGW_APP_QX_QXZHYJ
    <if test="_parameter != null">
      <include refid="Example_Where_Clause" />
    </if>
  </delete>
  <insert id="insert" parameterType="com.lnsoft.module.qx.qxzhyj.pojo.BgwAppQxQxzhyj">
    <!--
      WARNING - @mbggenerated
      This element is automatically generated by MyBatis Generator, do not modify.
      This element was generated on Fri Nov 16 16:29:01 CST 2018.
    -->
    insert into BGW_APP_QX_QXZHYJ (YJXH, AREANAME, SIGNALNAME, 
      YJTITLE, YJCONTENT, ISSUEDATE, 
      FREETIME, STA_NAME, CODE, 
      CODES, SIGNALTYPE, AREA
      )
    values (#{yjxh,jdbcType=DECIMAL}, #{areaname,jdbcType=VARCHAR}, #{signalname,jdbcType=VARCHAR}, 
      #{yjtitle,jdbcType=VARCHAR}, #{yjcontent,jdbcType=VARCHAR}, #{issuedate,jdbcType=TIMESTAMP}, 
      #{freetime,jdbcType=TIMESTAMP}, #{staName,jdbcType=VARCHAR}, #{code,jdbcType=VARCHAR}, 
      #{codes,jdbcType=VARCHAR}, #{signaltype,jdbcType=VARCHAR}, #{area,jdbcType=VARCHAR}
      )
  </insert>
  <insert id="insertSelective" parameterType="com.lnsoft.module.qx.qxzhyj.pojo.BgwAppQxQxzhyj">
    <!--
      WARNING - @mbggenerated
      This element is automatically generated by MyBatis Generator, do not modify.
      This element was generated on Fri Nov 16 16:29:01 CST 2018.
    -->
    insert into BGW_APP_QX_QXZHYJ
    <trim prefix="(" suffix=")" suffixOverrides=",">
      <if test="yjxh != null">
        YJXH,
      </if>
      <if test="areaname != null">
        AREANAME,
      </if>
      <if test="signalname != null">
        SIGNALNAME,
      </if>
      <if test="yjtitle != null">
        YJTITLE,
      </if>
      <if test="yjcontent != null">
        YJCONTENT,
      </if>
      <if test="issuedate != null">
        ISSUEDATE,
      </if>
      <if test="freetime != null">
        FREETIME,
      </if>
      <if test="staName != null">
        STA_NAME,
      </if>
      <if test="code != null">
        CODE,
      </if>
      <if test="codes != null">
        CODES,
      </if>
      <if test="signaltype != null">
        SIGNALTYPE,
      </if>
      <if test="area != null">
        AREA,
      </if>
    </trim>
    <trim prefix="values (" suffix=")" suffixOverrides=",">
      <if test="yjxh != null">
        #{yjxh,jdbcType=DECIMAL},
      </if>
      <if test="areaname != null">
        #{areaname,jdbcType=VARCHAR},
      </if>
      <if test="signalname != null">
        #{signalname,jdbcType=VARCHAR},
      </if>
      <if test="yjtitle != null">
        #{yjtitle,jdbcType=VARCHAR},
      </if>
      <if test="yjcontent != null">
        #{yjcontent,jdbcType=VARCHAR},
      </if>
      <if test="issuedate != null">
        #{issuedate,jdbcType=TIMESTAMP},
      </if>
      <if test="freetime != null">
        #{freetime,jdbcType=TIMESTAMP},
      </if>
      <if test="staName != null">
        #{staName,jdbcType=VARCHAR},
      </if>
      <if test="code != null">
        #{code,jdbcType=VARCHAR},
      </if>
      <if test="codes != null">
        #{codes,jdbcType=VARCHAR},
      </if>
      <if test="signaltype != null">
        #{signaltype,jdbcType=VARCHAR},
      </if>
      <if test="area != null">
        #{area,jdbcType=VARCHAR},
      </if>
    </trim>
  </insert>
  <select id="countByExample" parameterType="com.lnsoft.module.qx.qxzhyj.pojo.BgwAppQxQxzhyjExample" resultType="java.lang.Integer">
    <!--
      WARNING - @mbggenerated
      This element is automatically generated by MyBatis Generator, do not modify.
      This element was generated on Fri Nov 16 16:29:01 CST 2018.
    -->
    select count(*) from BGW_APP_QX_QXZHYJ
    <if test="_parameter != null">
      <include refid="Example_Where_Clause" />
    </if>
  </select>
  <update id="updateByExampleSelective" parameterType="map">
    <!--
      WARNING - @mbggenerated
      This element is automatically generated by MyBatis Generator, do not modify.
      This element was generated on Fri Nov 16 16:29:01 CST 2018.
    -->
    update BGW_APP_QX_QXZHYJ
    <set>
      <if test="record.yjxh != null">
        YJXH = #{record.yjxh,jdbcType=DECIMAL},
      </if>
      <if test="record.areaname != null">
        AREANAME = #{record.areaname,jdbcType=VARCHAR},
      </if>
      <if test="record.signalname != null">
        SIGNALNAME = #{record.signalname,jdbcType=VARCHAR},
      </if>
      <if test="record.yjtitle != null">
        YJTITLE = #{record.yjtitle,jdbcType=VARCHAR},
      </if>
      <if test="record.yjcontent != null">
        YJCONTENT = #{record.yjcontent,jdbcType=VARCHAR},
      </if>
      <if test="record.issuedate != null">
        ISSUEDATE = #{record.issuedate,jdbcType=TIMESTAMP},
      </if>
      <if test="record.freetime != null">
        FREETIME = #{record.freetime,jdbcType=TIMESTAMP},
      </if>
      <if test="record.staName != null">
        STA_NAME = #{record.staName,jdbcType=VARCHAR},
      </if>
      <if test="record.code != null">
        CODE = #{record.code,jdbcType=VARCHAR},
      </if>
      <if test="record.codes != null">
        CODES = #{record.codes,jdbcType=VARCHAR},
      </if>
      <if test="record.signaltype != null">
        SIGNALTYPE = #{record.signaltype,jdbcType=VARCHAR},
      </if>
      <if test="record.area != null">
        AREA = #{record.area,jdbcType=VARCHAR},
      </if>
    </set>
    <if test="_parameter != null">
      <include refid="Update_By_Example_Where_Clause" />
    </if>
  </update>
  <update id="updateByExample" parameterType="map">
    <!--
      WARNING - @mbggenerated
      This element is automatically generated by MyBatis Generator, do not modify.
      This element was generated on Fri Nov 16 16:29:01 CST 2018.
    -->
    update BGW_APP_QX_QXZHYJ
    set YJXH = #{record.yjxh,jdbcType=DECIMAL},
      AREANAME = #{record.areaname,jdbcType=VARCHAR},
      SIGNALNAME = #{record.signalname,jdbcType=VARCHAR},
      YJTITLE = #{record.yjtitle,jdbcType=VARCHAR},
      YJCONTENT = #{record.yjcontent,jdbcType=VARCHAR},
      ISSUEDATE = #{record.issuedate,jdbcType=TIMESTAMP},
      FREETIME = #{record.freetime,jdbcType=TIMESTAMP},
      STA_NAME = #{record.staName,jdbcType=VARCHAR},
      CODE = #{record.code,jdbcType=VARCHAR},
      CODES = #{record.codes,jdbcType=VARCHAR},
      SIGNALTYPE = #{record.signaltype,jdbcType=VARCHAR},
      AREA = #{record.area,jdbcType=VARCHAR}
    <if test="_parameter != null">
      <include refid="Update_By_Example_Where_Clause" />
    </if>
  </update>
</mapper>