<?xml version="1.0" encoding="UTF-8"?>
<!DOCTYPE mapper PUBLIC "-//mybatis.org//DTD Mapper 3.0//EN" "http://mybatis.org/dtd/mybatis-3-mapper.dtd">
<mapper namespace="com.lnsoft.module.ddjc.mapper.DdjcKggcsbjfDataMapper">
  <resultMap id="BaseResultMap" type="com.lnsoft.module.ddjc.pojo.DdjcKggcsbjfData">
    <!--
      WARNING - @mbggenerated
      This element is automatically generated by MyBatis Generator, do not modify.
      This element was generated on Fri Nov 16 16:13:35 CST 2018.
    -->
    <id column="SJID" jdbcType="VARCHAR" property="sjid" />
    <result column="YSJL_ID" jdbcType="VARCHAR" property="ysjlId" />
    <result column="XH" jdbcType="VARCHAR" property="xh" />
    <result column="DYDJ" jdbcType="VARCHAR" property="dydj" />
    <result column="JGMC" jdbcType="VARCHAR" property="jgmc" />
    <result column="SBMC" jdbcType="VARCHAR" property="sbmc" />
    <result column="JCDMC" jdbcType="VARCHAR" property="jcdmc" />
    <result column="JCBW" jdbcType="VARCHAR" property="jcbw" />
    <result column="YSSJWJ" jdbcType="VARCHAR" property="yssjwj" />
    <result column="BZZY" jdbcType="VARCHAR" property="bzzy" />
    <result column="ZDXHFZ" jdbcType="VARCHAR" property="zdxhfz" />
    <result column="ZDXHFZWZ" jdbcType="VARCHAR" property="zdxhfzwz" />
    <result column="XXMSYFX" jdbcType="VARCHAR" property="xxmsyfx" />
    <result column="JL" jdbcType="VARCHAR" property="jl" />
    <result column="SBID" jdbcType="VARCHAR" property="sbid" />
    <result column="JCDID" jdbcType="VARCHAR" property="jcdid" />
    <result column="SAVE_PATH" jdbcType="VARCHAR" property="savePath" />
  </resultMap>
  <sql id="Example_Where_Clause">
    <!--
      WARNING - @mbggenerated
      This element is automatically generated by MyBatis Generator, do not modify.
      This element was generated on Fri Nov 16 16:13:35 CST 2018.
    -->
    <where>
      <foreach collection="oredCriteria" item="criteria" separator="or">
        <if test="criteria.valid">
          <trim prefix="(" prefixOverrides="and" suffix=")">
            <foreach collection="criteria.criteria" item="criterion">
              <choose>
                <when test="criterion.noValue">
                  and ${criterion.condition}
                </when>
                <when test="criterion.singleValue">
                  and ${criterion.condition} #{criterion.value}
                </when>
                <when test="criterion.betweenValue">
                  and ${criterion.condition} #{criterion.value} and #{criterion.secondValue}
                </when>
                <when test="criterion.listValue">
                  and ${criterion.condition}
                  <foreach close=")" collection="criterion.value" item="listItem" open="(" separator=",">
                    #{listItem}
                  </foreach>
                </when>
              </choose>
            </foreach>
          </trim>
        </if>
      </foreach>
    </where>
  </sql>
  <sql id="Update_By_Example_Where_Clause">
    <!--
      WARNING - @mbggenerated
      This element is automatically generated by MyBatis Generator, do not modify.
      This element was generated on Fri Nov 16 16:13:35 CST 2018.
    -->
    <where>
      <foreach collection="example.oredCriteria" item="criteria" separator="or">
        <if test="criteria.valid">
          <trim prefix="(" prefixOverrides="and" suffix=")">
            <foreach collection="criteria.criteria" item="criterion">
              <choose>
                <when test="criterion.noValue">
                  and ${criterion.condition}
                </when>
                <when test="criterion.singleValue">
                  and ${criterion.condition} #{criterion.value}
                </when>
                <when test="criterion.betweenValue">
                  and ${criterion.condition} #{criterion.value} and #{criterion.secondValue}
                </when>
                <when test="criterion.listValue">
                  and ${criterion.condition}
                  <foreach close=")" collection="criterion.value" item="listItem" open="(" separator=",">
                    #{listItem}
                  </foreach>
                </when>
              </choose>
            </foreach>
          </trim>
        </if>
      </foreach>
    </where>
  </sql>
  <sql id="Base_Column_List">
    <!--
      WARNING - @mbggenerated
      This element is automatically generated by MyBatis Generator, do not modify.
      This element was generated on Fri Nov 16 16:13:35 CST 2018.
    -->
    SJID, YSJL_ID, XH, DYDJ, JGMC, SBMC, JCDMC, JCBW, YSSJWJ, BZZY, ZDXHFZ, ZDXHFZWZ, 
    XXMSYFX, JL, SBID, JCDID, SAVE_PATH
  </sql>
  <select id="selectByExample" parameterType="com.lnsoft.module.ddjc.pojo.DdjcKggcsbjfDataExample" resultMap="BaseResultMap">
    <!--
      WARNING - @mbggenerated
      This element is automatically generated by MyBatis Generator, do not modify.
      This element was generated on Fri Nov 16 16:13:35 CST 2018.
    -->
    select
    <if test="distinct">
      distinct
    </if>
    <include refid="Base_Column_List" />
    from DDJC_KGGCSBJF_DATA
    <if test="_parameter != null">
      <include refid="Example_Where_Clause" />
    </if>
    <if test="orderByClause != null">
      order by ${orderByClause}
    </if>
  </select>
  <select id="selectByPrimaryKey" parameterType="java.lang.String" resultMap="BaseResultMap">
    <!--
      WARNING - @mbggenerated
      This element is automatically generated by MyBatis Generator, do not modify.
      This element was generated on Fri Nov 16 16:13:35 CST 2018.
    -->
    select 
    <include refid="Base_Column_List" />
    from DDJC_KGGCSBJF_DATA
    where SJID = #{sjid,jdbcType=VARCHAR}
  </select>
  <delete id="deleteByPrimaryKey" parameterType="java.lang.String">
    <!--
      WARNING - @mbggenerated
      This element is automatically generated by MyBatis Generator, do not modify.
      This element was generated on Fri Nov 16 16:13:35 CST 2018.
    -->
    delete from DDJC_KGGCSBJF_DATA
    where SJID = #{sjid,jdbcType=VARCHAR}
  </delete>
  <delete id="deleteByExample" parameterType="com.lnsoft.module.ddjc.pojo.DdjcKggcsbjfDataExample">
    <!--
      WARNING - @mbggenerated
      This element is automatically generated by MyBatis Generator, do not modify.
      This element was generated on Fri Nov 16 16:13:35 CST 2018.
    -->
    delete from DDJC_KGGCSBJF_DATA
    <if test="_parameter != null">
      <include refid="Example_Where_Clause" />
    </if>
  </delete>
  <insert id="insert" parameterType="com.lnsoft.module.ddjc.pojo.DdjcKggcsbjfData">
    <!--
      WARNING - @mbggenerated
      This element is automatically generated by MyBatis Generator, do not modify.
      This element was generated on Fri Nov 16 16:13:35 CST 2018.
    -->
    insert into DDJC_KGGCSBJF_DATA (SJID, YSJL_ID, XH, 
      DYDJ, JGMC, SBMC, JCDMC, 
      JCBW, YSSJWJ, BZZY, 
      ZDXHFZ, ZDXHFZWZ, XXMSYFX, 
      JL, SBID, JCDID, SAVE_PATH
      )
    values (#{sjid,jdbcType=VARCHAR}, #{ysjlId,jdbcType=VARCHAR}, #{xh,jdbcType=VARCHAR}, 
      #{dydj,jdbcType=VARCHAR}, #{jgmc,jdbcType=VARCHAR}, #{sbmc,jdbcType=VARCHAR}, #{jcdmc,jdbcType=VARCHAR}, 
      #{jcbw,jdbcType=VARCHAR}, #{yssjwj,jdbcType=VARCHAR}, #{bzzy,jdbcType=VARCHAR}, 
      #{zdxhfz,jdbcType=VARCHAR}, #{zdxhfzwz,jdbcType=VARCHAR}, #{xxmsyfx,jdbcType=VARCHAR}, 
      #{jl,jdbcType=VARCHAR}, #{sbid,jdbcType=VARCHAR}, #{jcdid,jdbcType=VARCHAR}, #{savePath,jdbcType=VARCHAR}
      )
  </insert>
  <insert id="insertSelective" parameterType="com.lnsoft.module.ddjc.pojo.DdjcKggcsbjfData">
    <!--
      WARNING - @mbggenerated
      This element is automatically generated by MyBatis Generator, do not modify.
      This element was generated on Fri Nov 16 16:13:35 CST 2018.
    -->
    insert into DDJC_KGGCSBJF_DATA
    <trim prefix="(" suffix=")" suffixOverrides=",">
      <if test="sjid != null">
        SJID,
      </if>
      <if test="ysjlId != null">
        YSJL_ID,
      </if>
      <if test="xh != null">
        XH,
      </if>
      <if test="dydj != null">
        DYDJ,
      </if>
      <if test="jgmc != null">
        JGMC,
      </if>
      <if test="sbmc != null">
        SBMC,
      </if>
      <if test="jcdmc != null">
        JCDMC,
      </if>
      <if test="jcbw != null">
        JCBW,
      </if>
      <if test="yssjwj != null">
        YSSJWJ,
      </if>
      <if test="bzzy != null">
        BZZY,
      </if>
      <if test="zdxhfz != null">
        ZDXHFZ,
      </if>
      <if test="zdxhfzwz != null">
        ZDXHFZWZ,
      </if>
      <if test="xxmsyfx != null">
        XXMSYFX,
      </if>
      <if test="jl != null">
        JL,
      </if>
      <if test="sbid != null">
        SBID,
      </if>
      <if test="jcdid != null">
        JCDID,
      </if>
      <if test="savePath != null">
        SAVE_PATH,
      </if>
    </trim>
    <trim prefix="values (" suffix=")" suffixOverrides=",">
      <if test="sjid != null">
        #{sjid,jdbcType=VARCHAR},
      </if>
      <if test="ysjlId != null">
        #{ysjlId,jdbcType=VARCHAR},
      </if>
      <if test="xh != null">
        #{xh,jdbcType=VARCHAR},
      </if>
      <if test="dydj != null">
        #{dydj,jdbcType=VARCHAR},
      </if>
      <if test="jgmc != null">
        #{jgmc,jdbcType=VARCHAR},
      </if>
      <if test="sbmc != null">
        #{sbmc,jdbcType=VARCHAR},
      </if>
      <if test="jcdmc != null">
        #{jcdmc,jdbcType=VARCHAR},
      </if>
      <if test="jcbw != null">
        #{jcbw,jdbcType=VARCHAR},
      </if>
      <if test="yssjwj != null">
        #{yssjwj,jdbcType=VARCHAR},
      </if>
      <if test="bzzy != null">
        #{bzzy,jdbcType=VARCHAR},
      </if>
      <if test="zdxhfz != null">
        #{zdxhfz,jdbcType=VARCHAR},
      </if>
      <if test="zdxhfzwz != null">
        #{zdxhfzwz,jdbcType=VARCHAR},
      </if>
      <if test="xxmsyfx != null">
        #{xxmsyfx,jdbcType=VARCHAR},
      </if>
      <if test="jl != null">
        #{jl,jdbcType=VARCHAR},
      </if>
      <if test="sbid != null">
        #{sbid,jdbcType=VARCHAR},
      </if>
      <if test="jcdid != null">
        #{jcdid,jdbcType=VARCHAR},
      </if>
      <if test="savePath != null">
        #{savePath,jdbcType=VARCHAR},
      </if>
    </trim>
  </insert>
  <select id="countByExample" parameterType="com.lnsoft.module.ddjc.pojo.DdjcKggcsbjfDataExample" resultType="java.lang.Integer">
    <!--
      WARNING - @mbggenerated
      This element is automatically generated by MyBatis Generator, do not modify.
      This element was generated on Fri Nov 16 16:13:35 CST 2018.
    -->
    select count(*) from DDJC_KGGCSBJF_DATA
    <if test="_parameter != null">
      <include refid="Example_Where_Clause" />
    </if>
  </select>
  <update id="updateByExampleSelective" parameterType="map">
    <!--
      WARNING - @mbggenerated
      This element is automatically generated by MyBatis Generator, do not modify.
      This element was generated on Fri Nov 16 16:13:35 CST 2018.
    -->
    update DDJC_KGGCSBJF_DATA
    <set>
      <if test="record.sjid != null">
        SJID = #{record.sjid,jdbcType=VARCHAR},
      </if>
      <if test="record.ysjlId != null">
        YSJL_ID = #{record.ysjlId,jdbcType=VARCHAR},
      </if>
      <if test="record.xh != null">
        XH = #{record.xh,jdbcType=VARCHAR},
      </if>
      <if test="record.dydj != null">
        DYDJ = #{record.dydj,jdbcType=VARCHAR},
      </if>
      <if test="record.jgmc != null">
        JGMC = #{record.jgmc,jdbcType=VARCHAR},
      </if>
      <if test="record.sbmc != null">
        SBMC = #{record.sbmc,jdbcType=VARCHAR},
      </if>
      <if test="record.jcdmc != null">
        JCDMC = #{record.jcdmc,jdbcType=VARCHAR},
      </if>
      <if test="record.jcbw != null">
        JCBW = #{record.jcbw,jdbcType=VARCHAR},
      </if>
      <if test="record.yssjwj != null">
        YSSJWJ = #{record.yssjwj,jdbcType=VARCHAR},
      </if>
      <if test="record.bzzy != null">
        BZZY = #{record.bzzy,jdbcType=VARCHAR},
      </if>
      <if test="record.zdxhfz != null">
        ZDXHFZ = #{record.zdxhfz,jdbcType=VARCHAR},
      </if>
      <if test="record.zdxhfzwz != null">
        ZDXHFZWZ = #{record.zdxhfzwz,jdbcType=VARCHAR},
      </if>
      <if test="record.xxmsyfx != null">
        XXMSYFX = #{record.xxmsyfx,jdbcType=VARCHAR},
      </if>
      <if test="record.jl != null">
        JL = #{record.jl,jdbcType=VARCHAR},
      </if>
      <if test="record.sbid != null">
        SBID = #{record.sbid,jdbcType=VARCHAR},
      </if>
      <if test="record.jcdid != null">
        JCDID = #{record.jcdid,jdbcType=VARCHAR},
      </if>
      <if test="record.savePath != null">
        SAVE_PATH = #{record.savePath,jdbcType=VARCHAR},
      </if>
    </set>
    <if test="_parameter != null">
      <include refid="Update_By_Example_Where_Clause" />
    </if>
  </update>
  <update id="updateByExample" parameterType="map">
    <!--
      WARNING - @mbggenerated
      This element is automatically generated by MyBatis Generator, do not modify.
      This element was generated on Fri Nov 16 16:13:35 CST 2018.
    -->
    update DDJC_KGGCSBJF_DATA
    set SJID = #{record.sjid,jdbcType=VARCHAR},
      YSJL_ID = #{record.ysjlId,jdbcType=VARCHAR},
      XH = #{record.xh,jdbcType=VARCHAR},
      DYDJ = #{record.dydj,jdbcType=VARCHAR},
      JGMC = #{record.jgmc,jdbcType=VARCHAR},
      SBMC = #{record.sbmc,jdbcType=VARCHAR},
      JCDMC = #{record.jcdmc,jdbcType=VARCHAR},
      JCBW = #{record.jcbw,jdbcType=VARCHAR},
      YSSJWJ = #{record.yssjwj,jdbcType=VARCHAR},
      BZZY = #{record.bzzy,jdbcType=VARCHAR},
      ZDXHFZ = #{record.zdxhfz,jdbcType=VARCHAR},
      ZDXHFZWZ = #{record.zdxhfzwz,jdbcType=VARCHAR},
      XXMSYFX = #{record.xxmsyfx,jdbcType=VARCHAR},
      JL = #{record.jl,jdbcType=VARCHAR},
      SBID = #{record.sbid,jdbcType=VARCHAR},
      JCDID = #{record.jcdid,jdbcType=VARCHAR},
      SAVE_PATH = #{record.savePath,jdbcType=VARCHAR}
    <if test="_parameter != null">
      <include refid="Update_By_Example_Where_Clause" />
    </if>
  </update>
  <update id="updateByPrimaryKeySelective" parameterType="com.lnsoft.module.ddjc.pojo.DdjcKggcsbjfData">
    <!--
      WARNING - @mbggenerated
      This element is automatically generated by MyBatis Generator, do not modify.
      This element was generated on Fri Nov 16 16:13:35 CST 2018.
    -->
    update DDJC_KGGCSBJF_DATA
    <set>
      <if test="ysjlId != null">
        YSJL_ID = #{ysjlId,jdbcType=VARCHAR},
      </if>
      <if test="xh != null">
        XH = #{xh,jdbcType=VARCHAR},
      </if>
      <if test="dydj != null">
        DYDJ = #{dydj,jdbcType=VARCHAR},
      </if>
      <if test="jgmc != null">
        JGMC = #{jgmc,jdbcType=VARCHAR},
      </if>
      <if test="sbmc != null">
        SBMC = #{sbmc,jdbcType=VARCHAR},
      </if>
      <if test="jcdmc != null">
        JCDMC = #{jcdmc,jdbcType=VARCHAR},
      </if>
      <if test="jcbw != null">
        JCBW = #{jcbw,jdbcType=VARCHAR},
      </if>
      <if test="yssjwj != null">
        YSSJWJ = #{yssjwj,jdbcType=VARCHAR},
      </if>
      <if test="bzzy != null">
        BZZY = #{bzzy,jdbcType=VARCHAR},
      </if>
      <if test="zdxhfz != null">
        ZDXHFZ = #{zdxhfz,jdbcType=VARCHAR},
      </if>
      <if test="zdxhfzwz != null">
        ZDXHFZWZ = #{zdxhfzwz,jdbcType=VARCHAR},
      </if>
      <if test="xxmsyfx != null">
        XXMSYFX = #{xxmsyfx,jdbcType=VARCHAR},
      </if>
      <if test="jl != null">
        JL = #{jl,jdbcType=VARCHAR},
      </if>
      <if test="sbid != null">
        SBID = #{sbid,jdbcType=VARCHAR},
      </if>
      <if test="jcdid != null">
        JCDID = #{jcdid,jdbcType=VARCHAR},
      </if>
      <if test="savePath != null">
        SAVE_PATH = #{savePath,jdbcType=VARCHAR},
      </if>
    </set>
    where SJID = #{sjid,jdbcType=VARCHAR}
  </update>
  <update id="updateByPrimaryKey" parameterType="com.lnsoft.module.ddjc.pojo.DdjcKggcsbjfData">
    <!--
      WARNING - @mbggenerated
      This element is automatically generated by MyBatis Generator, do not modify.
      This element was generated on Fri Nov 16 16:13:35 CST 2018.
    -->
    update DDJC_KGGCSBJF_DATA
    set YSJL_ID = #{ysjlId,jdbcType=VARCHAR},
      XH = #{xh,jdbcType=VARCHAR},
      DYDJ = #{dydj,jdbcType=VARCHAR},
      JGMC = #{jgmc,jdbcType=VARCHAR},
      SBMC = #{sbmc,jdbcType=VARCHAR},
      JCDMC = #{jcdmc,jdbcType=VARCHAR},
      JCBW = #{jcbw,jdbcType=VARCHAR},
      YSSJWJ = #{yssjwj,jdbcType=VARCHAR},
      BZZY = #{bzzy,jdbcType=VARCHAR},
      ZDXHFZ = #{zdxhfz,jdbcType=VARCHAR},
      ZDXHFZWZ = #{zdxhfzwz,jdbcType=VARCHAR},
      XXMSYFX = #{xxmsyfx,jdbcType=VARCHAR},
      JL = #{jl,jdbcType=VARCHAR},
      SBID = #{sbid,jdbcType=VARCHAR},
      JCDID = #{jcdid,jdbcType=VARCHAR},
      SAVE_PATH = #{savePath,jdbcType=VARCHAR}
    where SJID = #{sjid,jdbcType=VARCHAR}
  </update>
</mapper>